{
  "seasonNo": 20,
  "label": "20기",
  "episodes": [
    { "ep": 146, "airDate": "2024-04-24" },
    { "ep": 147, "airDate": "2024-05-01" },
    { "ep": 148, "airDate": "2024-05-08" },
    { "ep": 149, "airDate": "2024-05-15" },
    { "ep": 150, "airDate": "2024-05-22" },
    { "ep": 151, "airDate": "2024-05-29" },
    { "ep": 152, "airDate": "2024-06-05" },
    { "ep": 153, "airDate": "2024-06-12" },
    { "ep": 154, "airDate": "2024-06-19" }
  ],
  "participants": [
    {
      "seasonNo": 20,
      "gender": "M",
      "handle": "영수",
      "photo": {
        "src": null,
        "alt": "나는 SOLO 20기 영수"
      },
      "instagram": "nogurchito",
      "profile": {
        "birthYear": 1986,
        "job": "소아청소년과 의사",
        "region": "서울",
        "traits": ["직장인 밴드 활동", "클래식 기타 연주"],
        "notableQuotes": [],
        "issues": []
      },
      "sources": [
        {
          "title": "나는 솔로 20기 출연자 정보 & 인스타 아이디",
          "url": "https://rich-dream.tistory.com/entry/%EB%82%98%EB%8A%94-%EC%86%94%EB%A1%9C%EB%82%98%EB%8A%94-solo-20%EA%B8%B0-%EC%B6%9C%EC%97%B0%EC%9E%90-%EC%A0%95%EB%B3%B4-%EC%9D%B8%EC%8A%A4%ED%83%80-%EC%95%84%EC%9D%B4%EB%94%94",
          "confidence": "medium"
        },
        {
          "title": "나는솔로 20기 직업 나이 학력 등 출연자 프로필",
          "url": "https://dealbom.com/entry/%EB%82%98%EB%8A%94%EC%86%94%EB%A1%9C-20%EA%B8%B0-%EC%A7%81%EC%97%85-%EB%82%98%EC%9D%B4-%ED%95%99%EB%A0%A5-%EB%93%B1-%EC%B6%9C%EC%97%B0%EC%9E%90-%ED%94%84%EB%A1%9C%ED%95%84-%EB%82%A8%EB%85%80-%EC%A0%84%EC%9B%90-%EC%B5%9C%EC%8B%A0-%EC%97%85%EB%8D%B0%EC%9D%B4%ED%8A%B8",
          "confidence": "medium"
        },
        {
          "title": "나는 솔로 20기 출연자 직업·나이·스펙 총정리",
          "url": "https://www.salgoonews.com/news/articleView.html?idxno=40014",
          "confidence": "high"
        },
        {
          "title": "나는 SOLO 20기 엄친남녀 커플들 탄생",
          "url": "https://v.daum.net/v/20240620060323860",
          "confidence": "high"
        }
      ],
      "finalChoice": null
    },
    {
      "seasonNo": 20,
      "gender": "M",
      "handle": "영호",
      "photo": {
        "src": null,
        "alt": "나는 SOLO 20기 영호"
      },
      "instagram": null,
      "profile": {
        "birthYear": 1990,
        "job": "현대엔지니어링 품질경영팀 재직",
        "region": "서울",
        "traits": ["35kg 감량 후 유지", "말한 것은 지키는 성격"],
        "notableQuotes": [],
        "issues": []
      },
      "sources": [
        {
          "title": "나는솔로 20기 직업 나이 학력 등 출연자 프로필",
          "url": "https://dealbom.com/entry/%EB%82%98%EB%8A%94%EC%86%94%EB%A1%9C-20%EA%B8%B0-%EC%A7%81%EC%97%85-%EB%82%98%EC%9D%B4-%ED%95%99%EB%A0%A5-%EB%93%B1-%EC%B6%9C%EC%97%B0%EC%9E%90-%ED%94%84%EB%A1%9C%ED%95%84-%EB%82%A8%EB%85%80-%EC%A0%84%EC%9B%90-%EC%B5%9C%EC%8B%A0-%EC%97%85%EB%8D%B0%EC%9D%B4%ED%8A%B8",
          "confidence": "medium"
        },
        {
          "title": "나는 솔로 20기 출연자 정보 & 인스타 아이디",
          "url": "https://rich-dream.tistory.com/entry/%EB%82%98%EB%8A%94-%EC%86%94%EB%A1%9C%EB%82%98%EB%8A%94-solo-20%EA%B8%B0-%EC%B6%9C%EC%97%B0%EC%9E%90-%EC%A0%95%EB%B3%B4-%EC%9D%B8%EC%8A%A4%ED%83%80-%EC%95%84%EC%9D%B4%EB%94%94",
          "confidence": "medium"
        },
        {
          "title": "나는 솔로 20기 출연자 직업·나이·스펙 총정리",
          "url": "https://www.salgoonews.com/news/articleView.html?idxno=40014",
          "confidence": "high"
        },
        {
          "title": "나는 SOLO 20기 엄친남녀 커플들 탄생",
          "url": "https://v.daum.net/v/20240620060323860",
          "confidence": "high"
        },
        {
          "title": "나는 SOLO 20기, 최종 선택, 정숙과 영호의 러브 스토리",
          "url": "https://seuni80.tistory.com/entry/%EB%82%98%EB%8A%94-SOLO-20%EA%B8%B0-%EC%B5%9C%EC%A2%85-%EC%84%A0%ED%83%9D-%EC%A0%95%EC%88%99%EA%B3%BC-%EC%98%81%ED%98%B8%EC%9D%98-%EB%9F%AC%EB%B8%8C-%EC%8A%A4%ED%86%A0%EB%A6%AC",
          "confidence": "medium"
        }
      ],
      "finalChoice": "정숙"
    },
    {
      "seasonNo": 20,
      "gender": "M",
      "handle": "영식",
      "photo": {
        "src": null,
        "alt": "나는 SOLO 20기 영식"
      },
      "instagram": "mingquu",
      "profile": {
        "birthYear": 1990,
        "job": "농협은행 근무",
        "region": "경기도 성남",
        "traits": ["다정한 성격", "상대방에게 잘 맞춰주는 편"],
        "notableQuotes": [],
        "issues": []
      },
      "sources": [
        {
          "title": "나는 솔로 20기 출연자 정보 & 인스타 아이디",
          "url": "https://rich-dream.tistory.com/entry/%EB%82%98%EB%8A%94-%EC%86%94%EB%A1%9C%EB%82%98%EB%8A%94-solo-20%EA%B8%B0-%EC%B6%9C%EC%97%B0%EC%9E%90-%EC%A0%95%EB%B3%B4-%EC%9D%B8%EC%8A%A4%ED%83%80-%EC%95%84%EC%9D%B4%EB%94%94",
          "confidence": "medium"
        },
        {
          "title": "나는솔로 20기 직업 나이 학력 등 출연자 프로필",
          "url": "https://dealbom.com/entry/%EB%82%98%EB%8A%94%EC%86%94%EB%A1%9C-20%EA%B8%B0-%EC%A7%81%EC%97%85-%EB%82%98%EC%9D%B4-%ED%95%99%EB%A0%A5-%EB%93%B1-%EC%B6%9C%EC%97%B0%EC%9E%90-%ED%94%84%EB%A1%9C%ED%95%84-%EB%82%A8%EB%85%80-%EC%A0%84%EC%9B%90-%EC%B5%9C%EC%8B%A0-%EC%97%85%EB%8D%B0%EC%9D%B4%ED%8A%B8",
          "confidence": "medium"
        },
        {
          "title": "나는 솔로 20기 출연자 직업·나이·스펙 총정리",
          "url": "https://www.salgoonews.com/news/articleView.html?idxno=40014",
          "confidence": "high"
        },
        {
          "title": "나는 SOLO 20기 엄친남녀 커플들 탄생",
          "url": "https://v.daum.net/v/20240620060323860",
          "confidence": "high"
        }
      ],
      "finalChoice": "현숙"
    },
    {
      "seasonNo": 20,
      "gender": "M",
      "handle": "영철",
      "photo": {
        "src": null,
        "alt": "나는 SOLO 20기 영철"
      },
      "instagram": "ry.ool",
      "profile": {
        "birthYear": 1984,
        "job": "인텔 프로세스 엔지니어",
        "region": "미국 오리건주 포틀랜드",
        "traits": ["미군 출신", "신학 석사", "정보설계 및 전략학 석사"],
        "notableQuotes": [],
        "issues": []
      },
      "sources": [
        {
          "title": "나는 솔로 20기 출연자 정보 & 인스타 아이디",
          "url": "https://rich-dream.tistory.com/entry/%EB%82%98%EB%8A%94-%EC%86%94%EB%A1%9C%EB%82%98%EB%8A%94-solo-20%EA%B8%B0-%EC%B6%9C%EC%97%B0%EC%9E%90-%EC%A0%95%EB%B3%B4-%EC%9D%B8%EC%8A%A4%ED%83%80-%EC%95%84%EC%9D%B4%EB%94%94",
          "confidence": "medium"
        },
        {
          "title": "나는솔로 20기 직업 나이 학력 등 출연자 프로필",
          "url": "https://dealbom.com/entry/%EB%82%98%EB%8A%94%EC%86%94%EB%A1%9C-20%EA%B8%B0-%EC%A7%81%EC%97%85-%EB%82%98%EC%9D%B4-%ED%95%99%EB%A0%A5-%EB%93%B1-%EC%B6%9C%EC%97%B0%EC%9E%90-%ED%94%84%EB%A1%9C%ED%95%84-%EB%82%A8%EB%85%80-%EC%A0%84%EC%9B%90-%EC%B5%9C%EC%8B%A0-%EC%97%85%EB%8D%B0%EC%9D%B4%ED%8A%B8",
          "confidence": "medium"
        },
        {
          "title": "나는 솔로 20기 출연자 직업·나이·스펙 총정리",
          "url": "https://www.salgoonews.com/news/articleView.html?idxno=40014",
          "confidence": "high"
        },
        {
          "title": "나는 SOLO 20기 엄친남녀 커플들 탄생",
          "url": "https://v.daum.net/v/20240620060323860",
          "confidence": "high"
        }
      ],
      "finalChoice": "영숙"
    },
    {
      "seasonNo": 20,
      "gender": "M",
      "handle": "광수",
      "photo": {
        "src": null,
        "alt": "나는 SOLO 20기 광수"
      },
      "instagram": "jeong.jy0321",
      "profile": {
        "birthYear": 1989,
        "job": "방탈출 카페 제작자",
        "region": "경기도 판교",
        "traits": ["과학고 조기졸업", "연세대학교 전기전자공학과"],
        "notableQuotes": [],
        "issues": []
      },
      "sources": [
        {
          "title": "나는 솔로 20기 출연자 정보 & 인스타 아이디",
          "url": "https://rich-dream.tistory.com/entry/%EB%82%98%EB%8A%94-%EC%86%94%EB%A1%9C%EB%82%98%EB%8A%94-solo-20%EA%B8%B0-%EC%B6%9C%EC%97%B0%EC%9E%90-%EC%A0%95%EB%B3%B4-%EC%9D%B8%EC%8A%A4%ED%83%80-%EC%95%84%EC%9D%B4%EB%94%94",
          "confidence": "medium"
        },
        {
          "title": "나는솔로 20기 직업 나이 학력 등 출연자 프로필",
          "url": "https://dealbom.com/entry/%EB%82%98%EB%8A%94%EC%86%94%EB%A1%9C-20%EA%B8%B0-%EC%A7%81%EC%97%85-%EB%82%98%EC%9D%B4-%ED%95%99%EB%A0%A5-%EB%93%B1-%EC%B6%9C%EC%97%B0%EC%9E%90-%ED%94%84%EB%A1%9C%ED%95%84-%EB%82%A8%EB%85%80-%EC%A0%84%EC%9B%90-%EC%B5%9C%EC%8B%A0-%EC%97%85%EB%8D%B0%EC%9D%B4%ED%8A%B8",
          "confidence": "medium"
        },
        {
          "title": "나는 솔로 20기 출연자 직업·나이·스펙 총정리",
          "url": "https://www.salgoonews.com/news/articleView.html?idxno=40014",
          "confidence": "high"
        },
        {
          "title": "나는 SOLO 20기 엄친남녀 커플들 탄생",
          "url": "https://v.daum.net/v/20240620060323860",
          "confidence": "high"
        }
      ],
      "finalChoice": null
    },
    {
      "seasonNo": 20,
      "gender": "M",
      "handle": "상철",
      "photo": {
        "src": null,
        "alt": "나는 SOLO 20기 상철"
      },
      "instagram": "mezzzzzzzini",
      "profile": {
        "birthYear": 1988,
        "job": "삼성전자 AI 개발자",
        "region": null,
        "traits": ["고려대학교 경영학과", "영어와 중국어 가능", "요리를 즐김"],
        "notableQuotes": [],
        "issues": []
      },
      "sources": [
        {
          "title": "나는 솔로 20기 출연자 정보 & 인스타 아이디",
          "url": "https://rich-dream.tistory.com/entry/%EB%82%98%EB%8A%94-%EC%86%94%EB%A1%9C%EB%82%98%EB%8A%94-solo-20%EA%B8%B0-%EC%B6%9C%EC%97%B0%EC%9E%90-%EC%A0%95%EB%B3%B4-%EC%9D%B8%EC%8A%A4%ED%83%80-%EC%95%84%EC%9D%B4%EB%94%94",
          "confidence": "medium"
        },
        {
          "title": "나는솔로 20기 직업 나이 학력 등 출연자 프로필",
          "url": "https://dealbom.com/entry/%EB%82%98%EB%8A%94%EC%86%94%EB%A1%9C-20%EA%B8%B0-%EC%A7%81%EC%97%85-%EB%82%98%EC%9D%B4-%ED%95%99%EB%A0%A5-%EB%93%B1-%EC%B6%9C%EC%97%B0%EC%9E%90-%ED%94%84%EB%A1%9C%ED%95%84-%EB%82%A8%EB%85%80-%EC%A0%84%EC%9B%90-%EC%B5%9C%EC%8B%A0-%EC%97%85%EB%8D%B0%EC%9D%B4%ED%8A%B8",
          "confidence": "medium"
        },
        {
          "title": "나는 솔로 20기 출연자 직업·나이·스펙 총정리",
          "url": "https://www.salgoonews.com/news/articleView.html?idxno=40014",
          "confidence": "high"
        },
        {
          "title": "나는 SOLO 20기 엄친남녀 커플들 탄생",
          "url": "https://v.daum.net/v/20240620060323860",
          "confidence": "high"
        }
      ],
      "finalChoice": "영자"
    },
    {
      "seasonNo": 20,
      "gender": "F",
      "handle": "영숙",
      "photo": {
        "src": null,
        "alt": "나는 SOLO 20기 영숙"
      },
      "instagram": "ddohyunnii",
      "profile": {
        "birthYear": 1991,
        "job": "현대제철 근무",
        "region": "서울 송파구",
        "traits": [
          "대원외고 출신",
          "고려대학교 경제학과",
          "좋아하면 아낌없이 다해주는 스타일"
        ],
        "notableQuotes": [],
        "issues": []
      },
      "sources": [
        {
          "title": "나는 솔로 20기 출연자 정보 & 인스타 아이디",
          "url": "https://rich-dream.tistory.com/entry/%EB%82%98%EB%8A%94-%EC%86%94%EB%A1%9C%EB%82%98%EB%8A%94-solo-20%EA%B8%B0-%EC%B6%9C%EC%97%B0%EC%9E%90-%EC%A0%95%EB%B3%B4-%EC%9D%B8%EC%8A%A4%ED%83%80-%EC%95%84%EC%9D%B4%EB%94%94",
          "confidence": "medium"
        },
        {
          "title": "나는솔로 20기 직업 나이 학력 등 출연자 프로필",
          "url": "https://dealbom.com/entry/%EB%82%98%EB%8A%94%EC%86%94%EB%A1%9C-20%EA%B8%B0-%EC%A7%81%EC%97%85-%EB%82%98%EC%9D%B4-%ED%95%99%EB%A0%A5-%EB%93%B1-%EC%B6%9C%EC%97%B0%EC%9E%90-%ED%94%84%EB%A1%9C%ED%95%84-%EB%82%A8%EB%85%80-%EC%A0%84%EC%9B%90-%EC%B5%9C%EC%8B%A0-%EC%97%85%EB%8D%B0%EC%9D%B4%ED%8A%B8",
          "confidence": "medium"
        },
        {
          "title": "나는 SOLO 20기 엄친남녀 커플들 탄생",
          "url": "https://v.daum.net/v/20240620060323860",
          "confidence": "high"
        }
      ],
      "finalChoice": "영철"
    },
    {
      "seasonNo": 20,
      "gender": "F",
      "handle": "정숙",
      "photo": {
        "src": null,
        "alt": "나는 SOLO 20기 정숙"
      },
      "instagram": "bitterpeach.kr",
      "profile": {
        "birthYear": 1987,
        "job": "LG전자 과장급 선임",
        "region": "서울 강남구",
        "traits": ["솔직한 성향", "별명은 탱탱볼"],
        "notableQuotes": [],
        "issues": []
      },
      "sources": [
        {
          "title": "나는 솔로 20기 출연자 정보 & 인스타 아이디",
          "url": "https://rich-dream.tistory.com/entry/%EB%82%98%EB%8A%94-%EC%86%94%EB%A1%9C%EB%82%98%EB%8A%94-solo-20%EA%B8%B0-%EC%B6%9C%EC%97%B0%EC%9E%90-%EC%A0%95%EB%B3%B4-%EC%9D%B8%EC%8A%A4%ED%83%80-%EC%95%84%EC%9D%B4%EB%94%94",
          "confidence": "medium"
        },
        {
          "title": "나는솔로 20기 직업 나이 학력 등 출연자 프로필",
          "url": "https://dealbom.com/entry/%EB%82%98%EB%8A%94%EC%86%94%EB%A1%9C-20%EA%B8%B0-%EC%A7%81%EC%97%85-%EB%82%98%EC%9D%B4-%ED%95%99%EB%A0%A5-%EB%93%B1-%EC%B6%9C%EC%97%B0%EC%9E%90-%ED%94%84%EB%A1%9C%ED%95%84-%EB%82%A8%EB%85%80-%EC%A0%84%EC%9B%90-%EC%B5%9C%EC%8B%A0-%EC%97%85%EB%8D%B0%EC%9D%B4%ED%8A%B8",
          "confidence": "medium"
        },
        {
          "title": "나는 SOLO 20기 엄친남녀 커플들 탄생",
          "url": "https://v.daum.net/v/20240620060323860",
          "confidence": "high"
        },
        {
          "title": "나는 SOLO 20기, 최종 선택, 정숙과 영호의 러브 스토리",
          "url": "https://seuni80.tistory.com/entry/%EB%82%98%EB%8A%94-SOLO-20%EA%B8%B0-%EC%B5%9C%EC%A2%85-%EC%84%A0%ED%83%9D-%EC%A0%95%EC%88%99%EA%B3%BC-%EC%98%81%ED%98%B8%EC%9D%98-%EB%9F%AC%EB%B8%8C-%EC%8A%A4%ED%86%A0%EB%A6%AC",
          "confidence": "medium"
        }
      ],
      "finalChoice": "영호"
    },
    {
      "seasonNo": 20,
      "gender": "F",
      "handle": "순자",
      "photo": {
        "src": null,
        "alt": "나는 SOLO 20기 순자"
      },
      "instagram": "r_ang22",
      "profile": {
        "birthYear": 1992,
        "job": "초등학교 교사",
        "region": "서울 강동구",
        "traits": ["서울교육대학교 졸업", "키 170cm", "서울 강동구 자가 보유"],
        "notableQuotes": [],
        "issues": []
      },
      "sources": [
        {
          "title": "나는 솔로 20기 출연자 정보 & 인스타 아이디",
          "url": "https://rich-dream.tistory.com/entry/%EB%82%98%EB%8A%94-%EC%86%94%EB%A1%9C%EB%82%98%EB%8A%94-solo-20%EA%B8%B0-%EC%B6%9C%EC%97%B0%EC%9E%90-%EC%A0%95%EB%B3%B4-%EC%9D%B8%EC%8A%A4%ED%83%80-%EC%95%84%EC%9D%B4%EB%94%94",
          "confidence": "medium"
        },
        {
          "title": "나는솔로 SOLO 20기 순자 직업 나이 인스타 바로가기",
          "url": "https://supermarch.tistory.com/entry/%EB%82%98%EB%8A%94%EC%86%94%EB%A1%9C-SOLO-20%EA%B8%B0-%EC%88%9C%EC%9E%90-%EC%A7%81%EC%97%85-%EB%82%98%EC%9D%B4-%EC%9D%B8%EC%8A%A4%ED%83%80-%EB%B0%94%EB%A1%9C%EA%B0%80%EA%B8%B0",
          "confidence": "medium"
        },
        {
          "title": "나는솔로 20기 직업 나이 학력 등 출연자 프로필",
          "url": "https://dealbom.com/entry/%EB%82%98%EB%8A%94%EC%86%94%EB%A1%9C-20%EA%B8%B0-%EC%A7%81%EC%97%85-%EB%82%98%EC%9D%B4-%ED%95%99%EB%A0%A5-%EB%93%B1-%EC%B6%9C%EC%97%B0%EC%9E%90-%ED%94%84%EB%A1%9C%ED%95%84-%EB%82%A8%EB%85%80-%EC%A0%84%EC%9B%90-%EC%B5%9C%EC%8B%A0-%EC%97%85%EB%8D%B0%EC%9D%B4%ED%8A%B8",
          "confidence": "medium"
        },
        {
          "title": "나는 SOLO 20기 엄친남녀 커플들 탄생",
          "url": "https://v.daum.net/v/20240620060323860",
          "confidence": "high"
        }
      ],
      "finalChoice": null
    },
    {
      "seasonNo": 20,
      "gender": "F",
      "handle": "옥순",
      "photo": {
        "src": null,
        "alt": "나는 SOLO 20기 옥순"
      },
      "instagram": "globetrotterheej",
      "profile": {
        "birthYear": 1988,
        "job": "구글 소프트 엔지니어",
        "region": "미국 뉴욕",
        "traits": ["코넬대학교 학사", "코넬대학교 석사", "39개국 여행"],
        "notableQuotes": [],
        "issues": []
      },
      "sources": [
        {
          "title": "나는 솔로 20기 출연자 정보 & 인스타 아이디",
          "url": "https://rich-dream.tistory.com/entry/%EB%82%98%EB%8A%94-%EC%86%94%EB%A1%9C%EB%82%98%EB%8A%94-solo-20%EA%B8%B0-%EC%B6%9C%EC%97%B0%EC%9E%90-%EC%A0%95%EB%B3%B4-%EC%9D%B8%EC%8A%A4%ED%83%80-%EC%95%84%EC%9D%B4%EB%94%94",
          "confidence": "medium"
        },
        {
          "title": "나는솔로 20기 직업 나이 학력 등 출연자 프로필",
          "url": "https://dealbom.com/entry/%EB%82%98%EB%8A%94%EC%86%94%EB%A1%9C-20%EA%B8%B0-%EC%A7%81%EC%97%85-%EB%82%98%EC%9D%B4-%ED%95%99%EB%A0%A5-%EB%93%B1-%EC%B6%9C%EC%97%B0%EC%9E%90-%ED%94%84%EB%A1%9C%ED%95%84-%EB%82%A8%EB%85%80-%EC%A0%84%EC%9B%90-%EC%B5%9C%EC%8B%A0-%EC%97%85%EB%8D%B0%EC%9D%B4%ED%8A%B8",
          "confidence": "medium"
        },
        {
          "title": "나는 SOLO 20기 엄친남녀 커플들 탄생",
          "url": "https://v.daum.net/v/20240620060323860",
          "confidence": "high"
        }
      ],
      "finalChoice": null
    },
    {
      "seasonNo": 20,
      "gender": "F",
      "handle": "영자",
      "photo": {
        "src": null,
        "alt": "나는 SOLO 20기 영자"
      },
      "instagram": "hyemnie",
      "profile": {
        "birthYear": 1994,
        "job": "롯데멤버스 금융 지원 서비스 재직",
        "region": null,
        "traits": ["연세대학교 경영학과", "시원하고 솔직한 성격"],
        "notableQuotes": [],
        "issues": []
      },
      "sources": [
        {
          "title": "나는 솔로 20기 출연자 정보 & 인스타 아이디",
          "url": "https://rich-dream.tistory.com/entry/%EB%82%98%EB%8A%94-%EC%86%94%EB%A1%9C%EB%82%98%EB%8A%94-solo-20%EA%B8%B0-%EC%B6%9C%EC%97%B0%EC%9E%90-%EC%A0%95%EB%B3%B4-%EC%9D%B8%EC%8A%A4%ED%83%80-%EC%95%84%EC%9D%B4%EB%94%94",
          "confidence": "medium"
        },
        {
          "title": "나는솔로 20기 직업 나이 학력 등 출연자 프로필",
          "url": "https://dealbom.com/entry/%EB%82%98%EB%8A%94%EC%86%94%EB%A1%9C-20%EA%B8%B0-%EC%A7%81%EC%97%85-%EB%82%98%EC%9D%B4-%ED%95%99%EB%A0%A5-%EB%93%B1-%EC%B6%9C%EC%97%B0%EC%9E%90-%ED%94%84%EB%A1%9C%ED%95%84-%EB%82%A8%EB%85%80-%EC%A0%84%EC%9B%90-%EC%B5%9C%EC%8B%A0-%EC%97%85%EB%8D%B0%EC%9D%B4%ED%8A%B8",
          "confidence": "medium"
        },
        {
          "title": "나는 SOLO 20기 엄친남녀 커플들 탄생",
          "url": "https://v.daum.net/v/20240620060323860",
          "confidence": "high"
        }
      ],
      "finalChoice": "상철"
    },
    {
      "seasonNo": 20,
      "gender": "F",
      "handle": "현숙",
      "photo": {
        "src": null,
        "alt": "나는 SOLO 20기 현숙"
      },
      "instagram": "jyujin_smile",
      "profile": {
        "birthYear": 1988,
        "job": "아모레퍼시픽 연구원",
        "region": "서울",
        "traits": [
          "서울대학교 약학대학 학사",
          "서울대학교 약학대학 석사",
          "감정기복이 별로 없는 편"
        ],
        "notableQuotes": [],
        "issues": []
      },
      "sources": [
        {
          "title": "나는 솔로 20기 출연자 정보 & 인스타 아이디",
          "url": "https://rich-dream.tistory.com/entry/%EB%82%98%EB%8A%94-%EC%86%94%EB%A1%9C%EB%82%98%EB%8A%94-solo-20%EA%B8%B0-%EC%B6%9C%EC%97%B0%EC%9E%90-%EC%A0%95%EB%B3%B4-%EC%9D%B8%EC%8A%A4%ED%83%80-%EC%95%84%EC%9D%B4%EB%94%94",
          "confidence": "medium"
        },
        {
          "title": "나는솔로 20기 직업 나이 학력 등 출연자 프로필",
          "url": "https://dealbom.com/entry/%EB%82%98%EB%8A%94%EC%86%94%EB%A1%9C-20%EA%B8%B0-%EC%A7%81%EC%97%85-%EB%82%98%EC%9D%B4-%ED%95%99%EB%A0%A5-%EB%93%B1-%EC%B6%9C%EC%97%B0%EC%9E%90-%ED%94%84%EB%A1%9C%ED%95%84-%EB%82%A8%EB%85%80-%EC%A0%84%EC%9B%90-%EC%B5%9C%EC%8B%A0-%EC%97%85%EB%8D%B0%EC%9D%B4%ED%8A%B8",
          "confidence": "medium"
        },
        {
          "title": "나는 SOLO 20기 엄친남녀 커플들 탄생",
          "url": "https://v.daum.net/v/20240620060323860",
          "confidence": "high"
        }
      ],
      "finalChoice": "영식"
    }
  ]
}
